pqos/__init__.py
pqos/allocation.py
pqos/capability.py
pqos/common.py
pqos/cpuinfo.py
pqos/devinfo.py
pqos/error.py
pqos/l2ca.py
pqos/l3ca.py
pqos/mba.py
pqos/monitoring.py
pqos/native_struct.py
pqos/pqos.py
pqos-5.0.0.dist-info/LICENSE
pqos-5.0.0.dist-info/METADATA
pqos-5.0.0.dist-info/WHEEL
pqos-5.0.0.dist-info/top_level.txt
pqos-5.0.0.dist-info/RECORD
