Metadata-Version: 2.1
Name: pqos
Version: 5.0.0
Summary: Python interface for Intel(R) RDT PQoS library
Home-page: https://github.com/intel/intel-cmt-cat
Author-email: Michal Aleksinski <michalx.aleksinski@intel.com>, Wojciech Andralojc <wojciechx.andralojc@intel.com>, Adrian Boczkowski <adrianx.boczkowski@intel.com>, Khawar Abbasi <khawar.abbasi@intel.com>
Maintainer-email: Michal Aleksinski <michalx.aleksinski@intel.com>
License: BSD LICENSE
Project-URL: Homepage, https://github.com/intel/intel-cmt-cat
Project-URL: Source Code, https://github.com/intel/intel-cmt-cat
Project-URL: Bug Tracker, https://github.com/intel/intel-cmt-cat/issues
Classifier: Programming Language :: Python :: 3
Classifier: Programming Language :: Python :: 3 :: Only
Classifier: Programming Language :: Python :: 3.6
Classifier: License :: OSI Approved :: BSD License
Requires-Python: >=3.6
License-File: LICENSE
Provides-Extra: dev
Requires-Dist: bandit ; extra == 'dev'
Requires-Dist: pylint ==2.17.0 ; extra == 'dev'
Requires-Dist: coverage ; extra == 'dev'
Requires-Dist: caniusepython3 ; extra == 'dev'
